{"rule":{"battleType":9,"totalTime":60000,"sceneId":100},"attacker":{"master":{"unitId":1,"settingId":1,"name":"满露凡","normalSkillId":900,"attrs":{"1":5931,"2":348165,"3":400,"4":8000,"5":0,"6":0,"7":2120,"8":60,"9":150,"10":0,"11":180,"12":240,"13":0,"14":0,"15":400,"16":0,"17":300,"18":120,"19":724,"20":240,"21":240,"22":626,"23":0,"24":10000,"25":20,"26":0,"27":0,"28":0,"29":0,"30":120,"31":120,"32":120,"33":60,"34":60,"35":60,"38":0,"39":0,"40":0,"41":0,"42":0,"43":0,"44":0,"45":0,"46":348165},"masterType":1},"heroes":[],"pets":[],"harems":[{"unitId":3,"slot":1,"settingId":23,"level":1}],"artifact":{"unitId":2,"settingId":1,"star":1},"heroCombineSettings":[],"generalVos":[{"unitId":4,"slot":1,"settingId":52,"weaponId":0},{"unitId":5,"slot":2,"settingId":61,"weaponId":0},{"unitId":6,"slot":3,"settingId":111,"weaponId":0},{"unitId":7,"slot":4,"settingId":30,"weaponId":0},{"unitId":8,"slot":5,"settingId":112,"weaponId":0},{"unitId":9,"slot":6,"settingId":27,"weaponId":0},{"unitId":10,"slot":7,"settingId":127,"weaponId":0},{"unitId":11,"slot":8,"settingId":128,"weaponId":0},{"unitId":12,"slot":9,"settingId":16,"weaponId":0},{"unitId":13,"slot":10,"settingId":17,"weaponId":0},{"unitId":14,"slot":11,"settingId":83,"weaponId":0},{"unitId":15,"slot":12,"settingId":106,"weaponId":0},{"unitId":16,"slot":13,"settingId":117,"weaponId":0},{"unitId":17,"slot":14,"settingId":116,"weaponId":0},{"unitId":18,"slot":15,"settingId":115,"weaponId":0},{"unitId":19,"slot":16,"settingId":118,"weaponId":0},{"unitId":20,"slot":17,"settingId":37,"weaponId":0},{"unitId":21,"slot":18,"settingId":53,"weaponId":0}],"catVos":[{"slot":0,"level":1,"amount":1},{"slot":1,"level":1,"amount":1},{"slot":2,"level":1,"amount":1},{"slot":3,"level":1,"amount":1},{"slot":4,"level":1,"amount":0},{"slot":5,"level":1,"amount":0}],"cloneVo":{"unitId":22,"fashionId":1},"recommend":0},"defender":{"master":{"unitId":-1,"settingId":1125,"name":"李傕","normalSkillId":125,"attrs":{"1":1182,"2":73722,"3":5000,"4":10000,"5":0,"6":0,"7":2400,"8":400,"9":400,"10":400,"11":800,"12":800,"13":0,"14":0,"15":1600,"16":1600,"17":1600,"18":1600,"19":1600,"20":1600,"21":800,"22":800,"23":0,"24":10000,"25":20,"26":0,"27":0,"28":0,"29":0,"30":0,"31":0,"32":0,"33":0,"34":0,"35":0,"38":0,"39":0,"40":0,"41":0,"42":0,"43":0,"44":0,"45":0,"46":73722},"masterType":2},"heroes":[],"pets":[],"harems":[{"unitId":-3,"slot":1,"settingId":21,"level":1},{"unitId":-4,"slot":2,"settingId":29,"level":1},{"unitId":-5,"slot":3,"settingId":34,"level":1}],"artifact":{"unitId":-2,"settingId":1,"star":0},"heroCombineSettings":[],"generalVos":[{"unitId":-6,"slot":1,"settingId":43,"weaponId":0},{"unitId":-7,"slot":2,"settingId":44,"weaponId":0},{"unitId":-8,"slot":3,"settingId":45,"weaponId":0},{"unitId":-9,"slot":4,"settingId":46,"weaponId":0},{"unitId":-10,"slot":5,"settingId":47,"weaponId":0},{"unitId":-11,"slot":6,"settingId":48,"weaponId":0}],"catVos":[{"slot":0,"level":1,"amount":35},{"slot":1,"level":1,"amount":35},{"slot":2,"level":1,"amount":35},{"slot":3,"level":1,"amount":35},{"slot":4,"level":1,"amount":35},{"slot":5,"level":1,"amount":35}],"recommend":0},"actions":[{"timestamp":1815,"type":0,"unitId":-6,"skillId":4043},{"timestamp":2013,"type":0,"unitId":-7,"skillId":4044},{"timestamp":2013,"type":0,"unitId":-8,"skillId":4045},{"timestamp":2013,"type":0,"unitId":-11,"skillId":4048},{"timestamp":2211,"type":0,"unitId":-6,"skillId":4043,"effect":[{"fighterId":1,"damageMap":{"1":501}}]},{"timestamp":2211,"type":0,"unitId":-9,"skillId":4046},{"timestamp":2211,"type":0,"unitId":-10,"skillId":4047},{"timestamp":2211,"type":0,"unitId":5,"skillId":4061},{"timestamp":2211,"type":0,"unitId":9,"skillId":4027},{"timestamp":2211,"type":0,"unitId":10,"skillId":4127},{"timestamp":2409,"type":0,"unitId":-7,"skillId":4044,"effect":[{"fighterId":1,"damageMap":{"1":529}}]},{"timestamp":2409,"type":0,"unitId":-8,"skillId":4045,"effect":[{"fighterId":1,"damageMap":{"1":578}}]},{"timestamp":2409,"type":0,"unitId":-11,"skillId":4048,"effect":[{"fighterId":1,"damageMap":{"1":529}}]},{"timestamp":2574,"type":0,"unitId":4,"skillId":4052},{"timestamp":2574,"type":0,"unitId":6,"skillId":4111},{"timestamp":2574,"type":0,"unitId":15,"skillId":4106},{"timestamp":2607,"type":0,"unitId":-9,"skillId":4046,"effect":[{"fighterId":1,"damageMap":{"1":618}}]},{"timestamp":2607,"type":0,"unitId":-10,"skillId":4047,"effect":[{"fighterId":1,"damageMap":{"1":612}}]},{"timestamp":2607,"type":0,"unitId":5,"skillId":4061,"effect":[{"fighterId":-1,"damageMap":{"1":9592}}]},{"timestamp":2607,"type":0,"unitId":9,"skillId":4027,"effect":[{"fighterId":-1,"damageMap":{"1":5908}}]},{"timestamp":2607,"type":0,"unitId":10,"skillId":4127,"effect":[{"fighterId":-1,"damageMap":{"1":6151}}]},{"timestamp":2937,"type":0,"unitId":8,"skillId":4112},{"timestamp":2937,"type":0,"unitId":21,"skillId":4053},{"timestamp":2970,"type":0,"unitId":4,"skillId":4052,"effect":[{"fighterId":-1,"damageMap":{"1":7035}}]},{"timestamp":2970,"type":0,"unitId":6,"skillId":4111,"effect":[{"fighterId":-1,"damageMap":{"1":7106}}]},{"timestamp":2970,"type":0,"unitId":15,"skillId":4106,"effect":[{"fighterId":-1,"damageMap":{"1":7248}}]},{"timestamp":3201,"type":0,"unitId":5,"skillId":4061},{"timestamp":3201,"type":0,"unitId":9,"skillId":4027},{"timestamp":3201,"type":0,"unitId":10,"skillId":4127},{"timestamp":3300,"type":0,"unitId":7,"skillId":4030},{"timestamp":3300,"type":0,"unitId":11,"skillId":4128},{"timestamp":3300,"type":0,"unitId":12,"skillId":4016},{"timestamp":3300,"type":0,"unitId":13,"skillId":4017},{"timestamp":3333,"type":0,"unitId":8,"skillId":4112,"effect":[{"fighterId":-1,"damageMap":{"1":8445}}]},{"timestamp":3333,"type":0,"unitId":21,"skillId":4053,"effect":[{"fighterId":-1,"damageMap":{"1":10151}}]},{"timestamp":3597,"type":0,"unitId":5,"skillId":4061,"effect":[{"fighterId":-1,"damageMap":{"1":9318}}]},{"timestamp":3597,"type":0,"unitId":9,"skillId":4027,"effect":[{"fighterId":-1,"damageMap":{"1":6334}}]}],"buffs":[],"rageChange":[],"states":[{"timestamp":0,"unitId":1,"effectId":84,"isAdd":1},{"timestamp":0,"unitId":1,"effectId":85,"isAdd":1},{"timestamp":0,"unitId":1,"effectId":81,"isAdd":1},{"timestamp":0,"unitId":1,"effectId":82,"isAdd":1},{"timestamp":0,"unitId":-1,"effectId":136,"isAdd":1},{"timestamp":0,"unitId":-1,"effectId":101,"isAdd":1},{"timestamp":0,"unitId":-1,"effectId":82,"isAdd":1},{"timestamp":0,"unitId":-1,"effectId":81,"isAdd":1}],"battleResult":0,"endTime":3597}